Metadata-Version: 1.1
Name: unimatrix.ext.guacamole
Version: 0.9
Summary: A Guacamole python client library.
Home-page: https://github.com/mohabusama/pyguacamole
Author: Mohab Usama
Author-email: UNKNOWN
License: The MIT License (MIT)
Platform: UNKNOWN
Classifier: Development Status :: 3 - Alpha
Classifier: Intended Audience :: Developers
Classifier: License :: OSI Approved :: MIT License
Classifier: Programming Language :: Python :: 2.7
Classifier: Programming Language :: Python :: 3.4
Classifier: Programming Language :: Python :: 3.5
Classifier: Programming Language :: Python :: 3.6
Classifier: Programming Language :: Python
Classifier: Topic :: Communications
Classifier: Topic :: Software Development :: Libraries :: Python Modules
